<xml version="1.0">
<dashboard>
	<widget field="folder down" type="Boolean" class="edu.wpi.first.smartdashboard.gui.elements.BooleanBox">
		<location x="144" y="272"/>
		<width>112</width>
		<height>48</height>
	</widget>
	<widget field="triz up" type="Boolean" class="edu.wpi.first.smartdashboard.gui.elements.BooleanBox">
		<location x="496" y="208"/>
		<width>80</width>
		<height>48</height>
	</widget>
	<widget field="boulder inside" type="Boolean" class="edu.wpi.first.smartdashboard.gui.elements.BooleanBox">
		<location x="288" y="208"/>
		<width>176</width>
		<height>112</height>
	</widget>
	<widget field="triz down" type="Boolean" class="edu.wpi.first.smartdashboard.gui.elements.BooleanBox">
		<location x="496" y="272"/>
		<width>96</width>
		<height>49</height>
	</widget>
	<widget field="folder up" type="Boolean" class="edu.wpi.first.smartdashboard.gui.elements.BooleanBox">
		<location x="144" y="208"/>
		<width>96</width>
		<height>49</height>
	</widget>
	<widget field="Defense" type="String Chooser" class="edu.wpi.first.smartdashboard.gui.elements.Chooser">
		<location x="16" y="155"/>
	</widget>
	<widget field="Auto" type="String Chooser" class="edu.wpi.first.smartdashboard.gui.elements.Chooser">
		<location x="112" y="16"/>
	</widget>
	<widget field="Location" type="String Chooser" class="edu.wpi.first.smartdashboard.gui.elements.Chooser">
		<location x="17" y="21"/>
	</widget>
	<widget field="RetractAll" type="Command" class="edu.wpi.first.smartdashboard.gui.elements.Command">
		<location x="147" y="160"/>
	</widget>
	<widget field="Reset gyro" type="Command" class="edu.wpi.first.smartdashboard.gui.elements.Command">
		<location x="608" y="208"/>
	</widget>
	<widget field="right distance" type="Number" class="edu.wpi.first.smartdashboard.gui.elements.TextBox">
		<location x="592" y="60"/>
	</widget>
	<widget field="folder distance" type="Number" class="edu.wpi.first.smartdashboard.gui.elements.TextBox">
		<location x="211" y="336"/>
	</widget>
	<widget field="angle with floor" type="Number" class="edu.wpi.first.smartdashboard.gui.elements.TextBox">
		<location x="320" y="96"/>
	</widget>
	<widget field="triz distance" type="Number" class="edu.wpi.first.smartdashboard.gui.elements.TextBox">
		<location x="432" y="336"/>
	</widget>
	<widget field="yaw angle" type="Number" class="edu.wpi.first.smartdashboard.gui.elements.TextBox">
		<location x="585" y="96"/>
	</widget>
	<widget field="left distance" type="Number" class="edu.wpi.first.smartdashboard.gui.elements.TextBox">
		<location x="320" y="60"/>
	</widget>
</dashboard>
<live-window>
</live-window>
	<hidden field="PIDTurnDriveByAngle.TOLERANCE"/>
	<hidden field="PIDTurnDriveByAngle.KI"/>
	<hidden field="PIDTurnDriveByAngle.ANGLE"/>
	<hidden field="PIDTurnDriveByAngle.KD"/>
	<hidden field="PIDTurnDriveByAngle"/>
	<hidden field="PIDTurnDriveByAngle.KP"/>
</xml>